[
{
	"artwork" : "yjd-1",
	"url" : "01.jpg",
	"artist" : "yjd",
	"ch-name" : "日月無聲 水過無痕",
	"en-name" : "La vie est un long fleuve tranquille",
	"intro" : "「日月無聲，水過無痕；三千繁華，彈指剎那。」",
	"data" : "金屬蝕刻凹版\n版數：50\n120 x 20 cm (不含框)\n2017",
	"class" : "fluid"
},
{
	"artwork" : "vk-1",
	"url" : "02.jpg",
	"artist" : "vk",
	"ch-name" : "Decoding",
	"en-name" : "",
	"intro" : "Decoding-為解碼之意。探討於拍攝當下時而為有目的，時而為淺意識而成，藉由回朔與探討當下的狀態與心境，解碼形成瞬間的起源與動機。",
	"data" : "數位微噴 <1/6>\n47 x 38 x 2.6 cm (含框尺寸)\n2017",
	"class" : ""
},
{
	"artwork" : "lsm-1",
	"url" : "03.jpg",
	"artist" : "lsm",
	"ch-name" : "紅嬋",
	"en-name" : "Shine",
	"intro" : "盯著花兒看的時候，會感覺到「氣息」\n含苞之後綻放，盛開之後凋零\n氣息遠在現象發生之前就吐露了。\n2009 , 11月",
	"data" : "30.5 x 23 cm\n色鉛筆、墨筆、紙\ncolor pencil、 ink 、paper\n2013",
	"class" : ""
},
{
	"artwork" : "lsm-2",
	"url" : "04.jpg",
	"artist" : "lsm",
	"ch-name" : "山牛蒡",
	"en-name" : "Vert Mousse",
	"intro" : "不知道為什麼，想要畫出捲曲的葉緣？\n不知道為什麼，渴望勾勒那細細的分岔！\n到底那每一個鋸齒間，藏著什麼魅力？\n2013，2月\n\n～是空間！\n每一個捲曲、每一道分岔、一段鋸齒⋯⋯都帶出一個空間。\n2014，6月",
	"data" : "30 x 21 cm\n色鉛筆、墨筆、紙\ncolor pencil、 ink 、paper\n2012",
	"class" : ""
},
{
	"artwork" : "hjw-1",
	"url" : "05.jpg",
	"artist" : "hjw",
	"ch-name" : "聽海",
	"en-name" : "花蓮東海岸",
	"intro" : "擔任國中美術老師工作多年，一直希望可以繼續從事藝術創作，在2017年2月一個和大學同學的寫生之旅開啟我的藝術創作。每個星期六日都是寫生日，用水彩寫生記錄我的家鄉，了解我的家鄉「花蓮」。這個行動將會一直持續下去，這是我愛我家鄉的方式。",
	"data" : "水彩\nWatercolor\n39 x 27 cm (不含框)\n2018",
	"class" : ""
},
{
	"artwork" : "hjw-2",
	"url" : "06.jpg",
	"artist" : "hjw",
	"ch-name" : "小漁港風情",
	"en-name" : "",
	"intro" : "擔任國中美術老師工作多年，一直希望可以繼續從事藝術創作，在2017年2月一個和大學同學的寫生之旅開啟我的藝術創作。每個星期六日都是寫生日，用水彩寫生記錄我的家鄉，了解我的家鄉「花蓮」。這個行動將會一直持續下去，這是我愛我家鄉的方式。",
	"data" : "水彩\nWatercolor\n39 x 27 cm (不含框)\n2018",
	"class" : ""
},
{
	"artwork" : "wyj-1",
	"url" : "07.jpg",
	"artist" : "wyj",
	"ch-name" : "此時此刻",
	"en-name" : "At This Moment",
	"intro" : "本作品以木質來模仿石頭的質感，在30x30x6cm的實木形體中，藉由凝視物質與心神之間的某種形質轉化，來寓意此時此刻的「當下即是」經驗。",
	"data" : "木\n30 x 30 x 6 cm (已含框或台座)\n2013",
	"class" : ""
},
{
	"artwork" : "lyl-1",
	"url" : "08.jpg",
	"artist" : "lyl",
	"ch-name" : "日夢者＃20",
	"en-name" : "",
	"intro" : "",
	"data" : "羊毛\n12 x 22 x 12 cm\n(含台座12 x 39 x 12 cm)\n2013",
	"class" : ""
},
{
	"artwork" : "vk-2",
	"url" : "09.jpg",
	"artist" : "vk",
	"ch-name" : "Step1-9",
	"en-name" : "",
	"intro" : "Step1-9 - 透過如電影敘事般的9張串連影像，解構出單一分鏡般之視覺分割意象。藉由觀者重組排列，構築形塑成自我意識與淺意識所主導掌控之獨立影像敘事，以其解碼原始結構與解構狀態過程中，經由第三者介入而形成的變化現象。",
	"data" : "數位微噴 <1/6>\n95 x 95 x 2.6 cm (含框尺寸)\n2017",
	"class" : ""
},
{
	"artwork" : "hdm-1",
	"url" : "10.jpg",
	"artist" : "hdm",
	"ch-name" : "初語",
	"en-name" : "",
	"intro" : "鳥鳴蟬聲，以春意盎然及夏日綠蔭的印象喧鬧著。矗立眺望著遠方，傳來暖陽升起後的第一聲，劃破綠意，共生共榮。",
	"data" : "大理石\n60 x 25 x 20 cm\n2019",
	"class" : ""
},
{
	"artwork" : "hjw-3",
	"url" : "11.jpg",
	"artist" : "hjw",
	"ch-name" : "百年九芎",
	"en-name" : "",
	"intro" : "擔任國中美術老師工作多年，一直希望可以繼續從事藝術創作，在2017年2月一個和大學同學的寫生之旅開啟我的藝術創作。每個星期六日都是寫生日，用水彩寫生記錄我的家鄉，了解我的家鄉「花蓮」。這個行動將會一直持續下去，這是我愛我家鄉的方式。",
	"data" : "水彩\nWatercolor\n54 x 39 cm (不含框)\n2019",
	"class" : ""
},
{
	"artwork" : "hjw-4",
	"url" : "12.jpg",
	"artist" : "hjw",
	"ch-name" : "花蓮大榮國小榕樹",
	"en-name" : "",
	"intro" : "擔任國中美術老師工作多年，一直希望可以繼續從事藝術創作，在2017年2月一個和大學同學的寫生之旅開啟我的藝術創作。每個星期六日都是寫生日，用水彩寫生記錄我的家鄉，了解我的家鄉「花蓮」。這個行動將會一直持續下去，這是我愛我家鄉的方式。",
	"data" : "水彩\nWatercolor\n54 x 39 cm (不含框)\n2019",
	"class" : ""
},
{
	"artwork" : "lsj-1",
	"url" : "13.jpg",
	"artist" : "lsj",
	"ch-name" : "澳底漁港的雲",
	"en-name" : "Clouds",
	"intro" : "這是一件以台北澳底漁港的海水所映照出來的雲, 港內的海水將天上的雲映照出來，也分離出彩虹一般的線條，大自然的水氣與光線的折射過程中不時映照出生活中的彩虹。也將我們眼睛視覺所見的東西分離出來，有時不是攝影器材所能補捉的眼識經驗，但在靜慮的觀察中，這些顏色的線條是無聲的跟我溝通著。",
	"data" : "壓克力顏料、畫布\nAcrylic paint on canvas\n53 cm x 65 cm (不含框)\n2019",
	"class" : ""
},
{
	"artwork" : "hcy-1",
	"url" : "14.jpg",
	"artist" : "hcy",
	"ch-name" : "富有餘",
	"en-name" : "Abundance of wealth",
	"intro" : "「九魚圖」是傳統藝術中的常見主題：鯉魚二字與「利」、「餘」諧音，又有「鯉躍龍門」的傳說；而九則與象徵長久不衰的「久」諧音，故受民間歡迎喜愛而廣見於生活之中。藝術家認為，這些圖像若以大眾化和流行性的角度來看，就像80至90年代的台版「普普藝術」，是市井小民的小確幸。\n\n本系列連作以喜丶樂丶富丶慶為題，其後各加上「有餘」二字，四幅作品共有九魚，象徵來年事事如意，完滿有餘。",
	"data" : "絹印\nSilkscreen\n50 x 50 x 4 cm (含框)\n2018",
	"class" : ""
},
{
	"artwork" : "cyw-1",
	"url" : "15.jpg",
	"artist" : "cyw",
	"ch-name" : "愛無所不在",
	"en-name" : "Love is all there is",
	"intro" : "瑜珈哲學視一切的總和為「一」，此「一」即創造、運行與再生的至上本體，或一般人所稱「上帝」、「老天」、「大宇宙」、「唯一真神」……，其本質為「愛」。因其為一切總和，故包含並超越所有時空而「無所不在、永恆不滅」，即梵語所稱Kevalam。稱念唱頌「愛無所不在」的「Bábá Nám Kevalam」，謂之「至上聖名唱頌」Kiirtana，同時佐以Lalita Mármika舞蹈則稱「靈性頌舞」。\n\n2019年6月中至7月初於Ánanda Márga阿南達瑪迦香港靜坐中心，於規律的靜坐與靜坐之間，在心中默唱或朗聲高歌Bábá Nám Kevalam的無盡喜悅的靈性波流中完成「紙上靈性頌舞Kiirtana on paper」系列創作，此為其一。謹此與世人同霑至上恩典。",
	"data" : "壓克力顏料、水彩紙\n38.6 x 38.6 cm (已含框)\n2019",
	"class" : ""
},
{
	"artwork" : "ww-1",
	"url" : "17.jpg",
	"artist" : "ww",
	"ch-name" : "福字盤上的魚",
	"en-name" : "A fish in the plate with the word \"fou\"",
	"intro" : "每次看到盤子上的魚頭，就想到魚還活著的樣子，阿彌陀佛。",
	"data" : "水印木刻版畫\nWater-based woodblock print\n30x22.5cm\n2019",
	"class" : ""
},
{
	"artwork" : "cyn-1",
	"url" : "18.jpg",
	"artist" : "cyn",
	"ch-name" : "夏荷白鷺",
	"en-name" : "Egret and Lotus in the Summer",
	"intro" : "鉛棒拓印的這系列作品起源於二○一七年一場意外。一七年因為意外骨折，耐著性子在家躺了好幾個月後，開始在家畫圖、刻版，但行動始終無法自如……為了將自己刻版的線條印出來，當時隨手以手邊的鉛棒以類似拓印邊款的方式拓印木板，意外發現這種方式比起一般水印木刻的印版方式更為方便、省時，又乾淨。當黑線稿拓印出來後，想起這幾年考察民間木版年畫時的經驗，民間藝人常常就以一張墨線主稿，透過不同的加工手法，便能將同一畫面變化出各種不同樣貌。因此，我試著將拓印後的黑線稿上彩，而這些由同張刻版印出的黑線稿也隨著手繪上彩變化出不同的畫面。",
	"data" : "鉛棒拓印上彩、宣紙\nGraphite stick rub on paper, Hand color\n27.5 x 35.3 cm (含框)\n2017",
	"class" : ""
},
{
	"artwork" : "lsm-3",
	"url" : "20.jpg",
	"artist" : "lsm",
	"ch-name" : "森林",
	"en-name" : "The Forest",
	"intro" : "2017年出發往北美洲旅行的時候，帶上了針線，這次想用針線來寫遊記。\n超市的牛皮紙袋、森林公園的目錄、以及商店的型錄⋯⋯旅行生活中撿拾的紙片，用針線串起它們，映出此地風景的意象。",
	"data" : "紙、線\npaper、sewing\n9.5 x 15 cm x 5張\n2017",
	"class" : ""
},
{
	"artwork" : "yjd-2",
	"url" : "16.jpg",
	"artist" : "yjd",
	"ch-name" : "永恆之城",
	"en-name" : "La cité éternelle",
	"intro" : "林保寶傳來新書《永恆之城》的書稿\n甚為悸動\n一種受過歐陸老靈魂洗禮的感動\n他將無數的親身體驗化為文字\n書寫出隱密角落裡永恆中的永恆\n\n方寸間\n是我穿越時間的窗口\n享受刻畫一點一線的當下\n將時間永遠留駐自己",
	"data" : "金屬蝕刻凹版\n版數：100\n贈《永恆之城》一書\n16cm x 17.8cm (不含框)\n2017",
	"class" : ""
},
{
	"artwork" : "kcs-1",
	"url" : "19.jpg",
	"artist" : "kcs",
	"ch-name" : "山水之舞",
	"en-name" : "",
	"intro" : "藉由山水的留白，凝練出原始舞蹈的線條。",
	"data" : "畫布油彩\n53 x 45.5 cm\n2018",
	"class" : ""
},
{
	"artwork" : "lsm-4",
	"url" : "21.jpg",
	"artist" : "lsm",
	"ch-name" : "海",
	"en-name" : "The Ocean",
	"intro" : "淘砂船緩慢的 彷彿紅色的小島\n蒼鷺在棧板上 晾曬浸濕的羽毛\n沙灘  浪潮  浮球  ⋯⋯\n岩岬交錯的後方是 英吉利海峽",
	"data" : "紙、線\npaper、sewing\n9.5 x 15 cm x 5張\n2017",
	"class" : ""
}
]